grambox/__init__.py
grambox/grambox.py
grambox-0.0.0.5.dist-info/METADATA
grambox-0.0.0.5.dist-info/WHEEL
grambox-0.0.0.5.dist-info/top_level.txt
grambox-0.0.0.5.dist-info/RECORD
