Metadata-Version: 2.4
Name: grambox
Version: 0.0.0.5
Author-email: HUSSEIN HAFEDH OBAID <husseun.selt@gmail.com>
License-Expression: MIT
Project-URL: Homepage, https://github.com/h98m/grambox
Project-URL: Issues, https://github.com/h98m/grambox/issues
Classifier: Programming Language :: Python :: 3
Classifier: Operating System :: OS Independent
Requires-Python: >=3.7
